garuda/__init__.py
garuda/constants.py
garuda/settings.py
garuda-0.0.1.dist-info/METADATA
garuda-0.0.1.dist-info/RECORD
garuda-0.0.1.dist-info/WHEEL
garuda-0.0.1.dist-info/top_level.txt
